smmap/__init__.py
smmap/buf.py
smmap/mman.py
smmap/util.py
smmap/test/__init__.py
smmap/test/lib.py
smmap/test/test_buf.py
smmap/test/test_mman.py
smmap/test/test_tutorial.py
smmap/test/test_util.py
smmap-6.0.0.dist-info/LICENSE
smmap-6.0.0.dist-info/METADATA
smmap-6.0.0.dist-info/WHEEL
smmap-6.0.0.dist-info/top_level.txt
smmap-6.0.0.dist-info/zip-safe
smmap-6.0.0.dist-info/RECORD
